_fasttrips.pyd
fasttrips/Assignment.py
fasttrips/Error.py
fasttrips/FastTrips.py
fasttrips/Logger.py
fasttrips/Passenger.py
fasttrips/PathSet.py
fasttrips/Performance.py
fasttrips/Route.py
fasttrips/Run.py
fasttrips/Stop.py
fasttrips/TAZ.py
fasttrips/Transfer.py
fasttrips/Trip.py
fasttrips/Util.py
fasttrips/__init__.py
fasttrips/Examples/test_scenario/demand_reg/Readme.md
fasttrips/Examples/test_scenario/demand_reg/config_ft.txt
fasttrips/Examples/test_scenario/demand_reg/pathweight_ft.txt
fasttrips/Examples/test_scenario/demand_reg/trip_list.txt
fasttrips/Examples/test_scenario/demand_twopaths/config_ft.py
fasttrips/Examples/test_scenario/demand_twopaths/config_ft.txt
fasttrips/Examples/test_scenario/demand_twopaths/household.txt
fasttrips/Examples/test_scenario/demand_twopaths/pathweight_ft.txt
fasttrips/Examples/test_scenario/demand_twopaths/person.txt
fasttrips/Examples/test_scenario/demand_twopaths/trip_list.txt
fasttrips/Examples/test_scenario/network/agency.txt
fasttrips/Examples/test_scenario/network/calendar.txt
fasttrips/Examples/test_scenario/network/drive_access_ft.txt
fasttrips/Examples/test_scenario/network/drive_access_points_ft.txt
fasttrips/Examples/test_scenario/network/fare_attributes.txt
fasttrips/Examples/test_scenario/network/fare_attributes_ft.txt
fasttrips/Examples/test_scenario/network/fare_periods_ft.txt
fasttrips/Examples/test_scenario/network/fare_rules.txt
fasttrips/Examples/test_scenario/network/fare_transfer_rules_ft.txt
fasttrips/Examples/test_scenario/network/node_coords.csv
fasttrips/Examples/test_scenario/network/routes.txt
fasttrips/Examples/test_scenario/network/routes_ft.txt
fasttrips/Examples/test_scenario/network/shapes.txt
fasttrips/Examples/test_scenario/network/stop_times.txt
fasttrips/Examples/test_scenario/network/stop_times_ft.txt
fasttrips/Examples/test_scenario/network/stops.txt
fasttrips/Examples/test_scenario/network/stops_ft.txt
fasttrips-1.0a14.dist-info/DESCRIPTION.rst
fasttrips-1.0a14.dist-info/METADATA
fasttrips-1.0a14.dist-info/RECORD
fasttrips-1.0a14.dist-info/WHEEL
fasttrips-1.0a14.dist-info/entry_points.txt
fasttrips-1.0a14.dist-info/metadata.json
fasttrips-1.0a14.dist-info/top_level.txt
