Metadata-Version: 2.0
Name: fasttrips
Version: 1.0a14
Summary: Dynamic Transit Assignment Model. Given a transit network and a list of transit demand, finds a pathset and chooses a path for each traveler.
Home-page: http://fast-trips.mtc.ca.gov/
Author: MTC, SFCTA & PSRC
Author-email: lzorn@mtc.ca.gov
License: Apache
Keywords: transit model dynamic passenger assignment simulation
Platform: UNKNOWN
Classifier: Development Status :: 3 - Alpha
Classifier: Intended Audience :: Other Audience
Classifier: Topic :: Scientific/Engineering
Classifier: License :: OSI Approved :: Apache Software License
Classifier: Programming Language :: Python :: 2
Classifier: Programming Language :: Python :: 2.7
Requires-Dist: pandas
Requires-Dist: transitfeed
